maker/__init__.py
maker/maker.py
qrmaker-1.0.3.dist-info/METADATA
qrmaker-1.0.3.dist-info/WHEEL
qrmaker-1.0.3.dist-info/entry_points.txt
qrmaker-1.0.3.dist-info/top_level.txt
qrmaker-1.0.3.dist-info/zip-safe
qrmaker-1.0.3.dist-info/RECORD
